pawk.py
pawk-0.8.1.dist-info/WHEEL
pawk-0.8.1.dist-info/entry_points.txt
pawk-0.8.1.dist-info/COPYING
pawk-0.8.1.dist-info/METADATA
pawk-0.8.1.dist-info/RECORD
