Metadata-Version: 2.1
Name: pawk
Version: 0.8.1
Summary: PAWK - A Python line processor (like AWK)
Home-page: https://github.com/alecthomas/pawk
License: MIT
Author: Alec Thomas
Author-email: alec@swapoff.org
Requires-Python: >=3.7
Classifier: License :: OSI Approved :: MIT License
Classifier: Operating System :: OS Independent
Classifier: Programming Language :: Python :: 3
Classifier: Programming Language :: Python :: 3.7
Classifier: Programming Language :: Python :: 3.8
Classifier: Programming Language :: Python :: 3.9
Classifier: Programming Language :: Python :: 3.10
Classifier: Programming Language :: Python :: 3.11
Classifier: Programming Language :: Python :: 3
Project-URL: Bug Tracker, https://github.com/alecthomas/pawk/issues
Project-URL: Repository, http://github.com/alecthomas/pawk
